{
	"version": "22",
	"name": "Java 22",
	"ga": "2024-03-15",
	"eol": "2024-09",
	"status": "DEV",
	"bytecode": "66.0",
	"documentation": {
		"notes": "http://jdk.java.net/22/release-notes",
		"api": "https://download.java.net/java/early_access/jdk22/docs/api/"
	},
	"scm": [
		{
			"type": "git",
			"url": "https://github.com/openjdk/jdk"
		}
	],
	"features": [
		{
			"title": "Statements before super(...)",
			"category": "lang",
			"preview": true,
			"revision": 1,
			"refs": [
				{
					"type": "JEP",
					"identifier": "447"
				}
			]
		},
		{
			"title": "Unnamed Variables & Patterns",
			"category": "lang",
			"refs": [
				{
					"type": "JEP",
					"identifier": "456"
				}
			]
		},
		{
			"title": "String Templates",
			"category": "lang",
			"preview": true,
			"revision": 2,
			"refs": [
				{
					"type": "JEP",
					"identifier": "459"
				},
				{
					"type": "AlmanacFeature",
					"identifier": "stringtemplates"
				}
			]
		},
		{
			"title": "Foreign Function & Memory API",
			"category": "api",
			"refs": [
				{
					"type": "JEP",
					"identifier": "454"
				}
			]
		}
	]
}
